seapeapea/__init__.py
seapeapea/cpp.lark
seapeapea-0.0.2.dist-info/LICENSE
seapeapea-0.0.2.dist-info/METADATA
seapeapea-0.0.2.dist-info/WHEEL
seapeapea-0.0.2.dist-info/entry_points.txt
seapeapea-0.0.2.dist-info/top_level.txt
seapeapea-0.0.2.dist-info/RECORD
