Metadata-Version: 2.1
Name: seapeapea
Version: 0.0.2
Summary: с++ to python transpiler
Home-page: https://github.com/mugiseyebrows/seapeapea
Author: Stanislav Doronin
Author-email: mugisbrows@gmail.com
License-File: LICENSE
Requires-Dist: lark
